{
  "signedContributors": [
    {
      "name": "ascorbic",
      "id": 213306,
      "comment_id": 4179242919,
      "created_at": "2026-04-02T17:09:21Z",
      "repoId": 1198246700,
      "pullRequestNo": 16
    },
    {
      "name": "JULJERYT",
      "id": 94785972,
      "comment_id": 4179289767,
      "created_at": "2026-04-02T17:17:49Z",
      "repoId": 1198246700,
      "pullRequestNo": 120
    },
    {
      "name": "bhubbard",
      "id": 3837,
      "comment_id": 4179468100,
      "created_at": "2026-04-02T17:49:33Z",
      "repoId": 1198246700,
      "pullRequestNo": 82
    },
    {
      "name": "RibasSu",
      "id": 97896193,
      "comment_id": 4179937620,
      "created_at": "2026-04-02T19:11:34Z",
      "repoId": 1198246700,
      "pullRequestNo": 109
    }
  ]
}